latestEarthquakeID/__init__.py
latestEarthquake_bmkg_Indonesia-0.0.4.dist-info/LICENSE
latestEarthquake_bmkg_Indonesia-0.0.4.dist-info/METADATA
latestEarthquake_bmkg_Indonesia-0.0.4.dist-info/WHEEL
latestEarthquake_bmkg_Indonesia-0.0.4.dist-info/top_level.txt
latestEarthquake_bmkg_Indonesia-0.0.4.dist-info/RECORD
